distinctipy/__init__.py
distinctipy/_colorsets_data.py
distinctipy/colorblind.py
distinctipy/colorsets.py
distinctipy/distinctipy.py
distinctipy/examples.py
distinctipy-1.3.4.dist-info/LICENSE
distinctipy-1.3.4.dist-info/METADATA
distinctipy-1.3.4.dist-info/WHEEL
distinctipy-1.3.4.dist-info/top_level.txt
distinctipy-1.3.4.dist-info/RECORD
