Metadata-Version: 2.1
Name: distinctipy
Version: 1.3.4
Summary: A lightweight package for generating visually distinct colours.
Author-email: Jack Roberts <jroberts@turing.ac.uk>
License: MIT License
Project-URL: Homepage, https://github.com/alan-turing-institute/distinctipy
Project-URL: Documentation, https://distinctipy.readthedocs.io/
Keywords: color,colour,palette,colormap,colorblind,colourblind
Classifier: Programming Language :: Python :: 3
Classifier: License :: OSI Approved :: MIT License
Classifier: Operating System :: OS Independent
Classifier: Topic :: Multimedia :: Graphics
Classifier: Topic :: Scientific/Engineering :: Visualization
Classifier: Topic :: Utilities
Classifier: Framework :: Matplotlib
Requires-Python: >=3.8
License-File: LICENSE
Requires-Dist: numpy>=1.16.3
Provides-Extra: extras
Requires-Dist: pandas>=0.24.2; extra == "extras"
Requires-Dist: matplotlib>=3.1.0; extra == "extras"
Provides-Extra: tests
Requires-Dist: black==22.6.0; extra == "tests"
Requires-Dist: codecov>=2.0.15; extra == "tests"
Requires-Dist: coverage>=5.3.1; extra == "tests"
Requires-Dist: flake8==4.0.1; extra == "tests"
Requires-Dist: isort==5.10.1; extra == "tests"
Requires-Dist: pytest>=4.6.0; extra == "tests"
Requires-Dist: pytest-cov>=2.9.0; extra == "tests"
Provides-Extra: docs
Requires-Dist: sphinx-rtd-theme>=0.2.3; extra == "docs"
Requires-Dist: nbsphinx>=0.8.0; extra == "docs"
Requires-Dist: ipython>=7.34.0; extra == "docs"
